avtagent/__init__.py
avtagent/agents.py
jamblaki_agent-0.1.0.dist-info/METADATA
jamblaki_agent-0.1.0.dist-info/WHEEL
jamblaki_agent-0.1.0.dist-info/top_level.txt
jamblaki_agent-0.1.0.dist-info/RECORD
