Metadata-Version: 2.1
Name: jamblaki_agent
Version: 0.1.0
Summary: A library for jamblaki agent
Author: jamblaki
Author-email: jamblaki@test.com
Classifier: Programming Language :: Python :: 3
Classifier: License :: OSI Approved :: MIT License
Classifier: Operating System :: OS Independent
Requires-Python: >=3.10
Requires-Dist: openai
Requires-Dist: pyautogen
